[
  {
    "name": "Etam World",
    "organization_id": "1"
  },
  {
    "name": "Ividata",
    "organization_id": "2"
  },
  {
    "name": "Ivizone",
    "organization_id": "3"
  },
  {
    "name": "Etam World",
    "organization_id": "4"
  },
  {
    "name": "Ividata",
    "organization_id": "5"
  },
  {
    "name": "Ivizone",
    "organization_id": "6"
  },
  {
    "name": "Etam World",
    "organization_id": "7"
  },
  {
    "name": "Ividata",
    "organization_id": "8"
  },
  {
    "name": "Ivizone",
    "organization_id": "9"
  },
  {
    "name": "Etam World",
    "organization_id": "10"
  },
  {
    "name": "Ividata",
    "organization_id": "11"
  },
  {
    "name": "Ivizone",
    "organization_id": "12"
  }
]
